warp/__init__.py
warp/mqtt_client.py
warp/mqtt_config.py
warp/warp3.py
warp/warp3_api.py
warpmqtt2api-0.1.1.dist-info/METADATA
warpmqtt2api-0.1.1.dist-info/WHEEL
warpmqtt2api-0.1.1.dist-info/entry_points.txt
warpmqtt2api-0.1.1.dist-info/licenses/LICENSE
warpmqtt2api-0.1.1.dist-info/RECORD
