Metadata-Version: 2.4
Name: WarpMQTT2Api
Version: 0.1.1
Dynamic: Summary
Project-URL: Home, https://github.com/WolfgangFahl/WarpMQTT2Api
Project-URL: Documentation, https://wiki.bitplan.com/index.php/WarpMQTT2Ap
Project-URL: Source, https://github.com/WolfgangFahl/WarpMQTT2Api
Author-email: Wolfgang Fahl <wf@bitplan.com>
Maintainer-email: Wolfgang Fahl <wf@bitplan.com>
License-Expression: Apache-2.0
License-File: LICENSE
Keywords: MQTT,PV surplus,Tinkerforge,Warp,Warp3,energy monitoring,home automation,smart charging,solar charging,wallbox integration
Classifier: Programming Language :: Python
Classifier: Programming Language :: Python :: 3.10
Classifier: Programming Language :: Python :: 3.11
Classifier: Programming Language :: Python :: 3.12
Classifier: Programming Language :: Python :: 3.13
Requires-Python: >=3.10
Requires-Dist: pybasemkit>=0.0.3
Requires-Dist: pylodstorage>=0.16.4
Provides-Extra: test
